django_cf_turnstile/__init__.py
django_cf_turnstile/apps.py
django_cf_turnstile/client.py
django_cf_turnstile/fields.py
django_cf_turnstile/widgets.py
django_cf_turnstile/templates/turnstile/js.html
django_cf_turnstile/templates/turnstile/widget_implicit.html
django_cf_turnstile-0.1.0.dist-info/licenses/LICENSE
django_cf_turnstile-0.1.0.dist-info/METADATA
django_cf_turnstile-0.1.0.dist-info/WHEEL
django_cf_turnstile-0.1.0.dist-info/top_level.txt
django_cf_turnstile-0.1.0.dist-info/RECORD
